LICENSE
README.md
argparse_subcommand.py
pyproject.toml
argparse_subcommand-1.2.dist-info/LICENSE
argparse_subcommand-1.2.dist-info/METADATA
argparse_subcommand-1.2.dist-info/WHEEL
argparse_subcommand-1.2.dist-info/RECORD
