Metadata-Version: 2.1
Name: argparse_subcommand
Version: 1.2
Summary: structure and simplify subcommand handling with argparse
Home-page: https://github.com/prechelt/argparse_subcommand
License: LICENSE
Keywords: argparse
Author: Lutz Prechelt
Requires-Python: >=3.7,<4.0
Classifier: Development Status :: 5 - Production/Stable
Classifier: License :: OSI Approved :: MIT License
Classifier: License :: Other/Proprietary License
Classifier: Operating System :: OS Independent
Classifier: Programming Language :: Python :: 3
Classifier: Programming Language :: Python :: 3.7
Classifier: Programming Language :: Python :: 3.8
Classifier: Programming Language :: Python :: 3.9
Classifier: Programming Language :: Python :: 3.10
Classifier: Programming Language :: Python :: 3.11
Classifier: Programming Language :: Python :: 3.12
Project-URL: Repository, https://github.com/prechelt/argparse_subcommand
